aioenkanetworkcard/enc_error.py
aioenkanetworkcard/encbanner.py
aioenkanetworkcard/src/assets/constant/ANEMO.png
aioenkanetworkcard/src/assets/constant/CLOSED.png
aioenkanetworkcard/src/assets/constant/CLOSED_BG.png
aioenkanetworkcard/src/assets/constant/CONSTATN_BG.png
aioenkanetworkcard/src/assets/constant/CRYO.png
aioenkanetworkcard/src/assets/constant/DENDRO.png
aioenkanetworkcard/src/assets/constant/ELECTRO.png
aioenkanetworkcard/src/assets/constant/ERROR.png
aioenkanetworkcard/src/assets/constant/GEO.png
aioenkanetworkcard/src/assets/constant/GYDRO.png
aioenkanetworkcard/src/assets/constant/PYRO.png
aioenkanetworkcard/src/assets/font/Genshin_Impact.ttf
aioenkanetworkcard/src/assets/icon/ANEMO.png
aioenkanetworkcard/src/assets/icon/ARTIFACT.png
aioenkanetworkcard/src/assets/icon/ATTACK.png
aioenkanetworkcard/src/assets/icon/ATTACK_PERCENT.png
aioenkanetworkcard/src/assets/icon/CHARGE_EFFICIENCY.png
aioenkanetworkcard/src/assets/icon/CRITICAL.png
aioenkanetworkcard/src/assets/icon/CRITICAL_HURT.png
aioenkanetworkcard/src/assets/icon/CRYO.png
aioenkanetworkcard/src/assets/icon/DEFENSE.png
aioenkanetworkcard/src/assets/icon/DEFENSE_PERCENT.png
aioenkanetworkcard/src/assets/icon/DENDRO.png
aioenkanetworkcard/src/assets/icon/ELECTRO.png
aioenkanetworkcard/src/assets/icon/FRIENDS.png
aioenkanetworkcard/src/assets/icon/GEO.png
aioenkanetworkcard/src/assets/icon/HEAL.png
aioenkanetworkcard/src/assets/icon/HEALED_ADD.png
aioenkanetworkcard/src/assets/icon/HP.png
aioenkanetworkcard/src/assets/icon/HP_PERCENT.png
aioenkanetworkcard/src/assets/icon/HYDRO.png
aioenkanetworkcard/src/assets/icon/MASTERY.png
aioenkanetworkcard/src/assets/icon/PHYSICAL_ADD_HURT.png
aioenkanetworkcard/src/assets/icon/PYRO.png
aioenkanetworkcard/src/assets/icon/SHIELD_COST_MINUS_RATIO.png
aioenkanetworkcard/src/assets/InfoCharter/AvatarMaska.png
aioenkanetworkcard/src/assets/InfoCharter/AvatarUser.png
aioenkanetworkcard/src/assets/InfoCharter/bg.png
aioenkanetworkcard-2.2.8.dist-info/WHEEL
aioenkanetworkcard-2.2.8.dist-info/METADATA
aioenkanetworkcard-2.2.8.dist-info/RECORD
